miditok/__init__.py
miditok/classes.py
miditok/constants.py
miditok/midi_tokenizer.py
miditok/tokenizer_training_iterator.py
miditok/attribute_controls/__init__.py
miditok/attribute_controls/bar_attribute_controls.py
miditok/attribute_controls/classes.py
miditok/attribute_controls/track_attribute_controls.py
miditok/data_augmentation/__init__.py
miditok/data_augmentation/data_augmentation.py
miditok/pytorch_data/__init__.py
miditok/pytorch_data/collators.py
miditok/pytorch_data/datasets.py
miditok/tokenizations/__init__.py
miditok/tokenizations/cp_word.py
miditok/tokenizations/midi_like.py
miditok/tokenizations/mmm.py
miditok/tokenizations/mumidi.py
miditok/tokenizations/octuple.py
miditok/tokenizations/pertok.py
miditok/tokenizations/remi.py
miditok/tokenizations/structured.py
miditok/tokenizations/tsd.py
miditok/utils/__init__.py
miditok/utils/split.py
miditok/utils/utils.py
miditok-3.0.6.dist-info/METADATA
miditok-3.0.6.dist-info/WHEEL
miditok-3.0.6.dist-info/licenses/LICENSE
miditok-3.0.6.dist-info/RECORD
