Metadata-Version: 2.4
Name: miditok
Version: 3.0.6
Summary: MIDI / symbolic music tokenizers for Deep Learning models.
Project-URL: Homepage, https://github.com/Natooz/MidiTok
Project-URL: Repository, https://github.com/Natooz/MidiTok.git
Project-URL: Documentation, https://miditok.readthedocs.io
Project-URL: Issues, https://github.com/Natooz/MidiTok/issues
Author: Nathan Fradet
License: MIT License
License-File: LICENSE
Keywords: artificial intelligence,deep learning,midi,mir,music,tokenization,transformer
Classifier: Intended Audience :: Developers
Classifier: Intended Audience :: Science/Research
Classifier: License :: OSI Approved :: MIT License
Classifier: Operating System :: OS Independent
Classifier: Programming Language :: Python
Classifier: Programming Language :: Python :: 3 :: Only
Classifier: Programming Language :: Python :: 3.9
Classifier: Programming Language :: Python :: 3.10
Classifier: Programming Language :: Python :: 3.11
Classifier: Programming Language :: Python :: 3.12
Classifier: Programming Language :: Python :: 3.13
Classifier: Topic :: Multimedia :: Sound/Audio :: MIDI
Classifier: Topic :: Scientific/Engineering :: Artificial Intelligence
Requires-Python: >=3.9
Requires-Dist: huggingface-hub>=0.16.4
Requires-Dist: numpy>=1.19
Requires-Dist: symusic>=0.5.0
Requires-Dist: tokenizers>=0.13.0
Requires-Dist: tqdm
Provides-Extra: docs
Requires-Dist: furo; extra == 'docs'
Requires-Dist: sphinx-copybutton; extra == 'docs'
Requires-Dist: torch; extra == 'docs'
Provides-Extra: tests
Requires-Dist: miditoolkit; extra == 'tests'
Requires-Dist: pytest-cov; extra == 'tests'
Requires-Dist: pytest-xdist[psutil]; extra == 'tests'
Requires-Dist: torch; extra == 'tests'
